lyse/__init__.py
lyse/__main__.py
lyse/__version__.py
lyse/analysis_subprocess.py
lyse/dataframe_utilities.py
lyse/desktop-app.json
lyse/edit_columns.ui
lyse/figure_manager.py
lyse/filebox.ui
lyse/lyse.ico
lyse/lyse.svg
lyse/main.ui
lyse/plot_window.ui
lyse/routinebox.ui
lyse/tempfile2clipboard.py
lyse-3.2.3.dist-info/LICENSE.txt
lyse-3.2.3.dist-info/METADATA
lyse-3.2.3.dist-info/WHEEL
lyse-3.2.3.dist-info/entry_points.txt
lyse-3.2.3.dist-info/top_level.txt
lyse-3.2.3.dist-info/RECORD
