Metadata-Version: 2.1
Name: lyse
Version: 3.2.3
Summary: Automated analysis queue for labscript suite experiments
Home-page: http://labscriptsuite.org
Author: The labscript suite community
Author-email: labscriptsuite@googlegroups.com
License: BSD
Project-URL: Source Code, https://github.com/labscript-suite/lyse
Project-URL: Download, https://github.com/labscript-suite/lyse/releases
Project-URL: Tracker, https://github.com/labscript-suite/lyse/issues
Keywords: experiment analysis automation
Classifier: License :: OSI Approved :: BSD License
Classifier: Programming Language :: Python :: 3 :: Only
Classifier: Programming Language :: Python :: 3.6
Classifier: Programming Language :: Python :: 3.7
Classifier: Programming Language :: Python :: 3.8
Classifier: Programming Language :: Python :: 3.9
Classifier: Programming Language :: Python :: 3.10
Classifier: Programming Language :: Python :: 3.11
Requires-Python: >=3.6
License-File: LICENSE.txt
Requires-Dist: desktop-app >=0.1.2
Requires-Dist: h5py
Requires-Dist: importlib-metadata
Requires-Dist: labscript-utils >=3.3.0
Requires-Dist: matplotlib
Requires-Dist: numpy
Requires-Dist: pandas >=0.21
Requires-Dist: qtutils >=2.2.2
Requires-Dist: scipy
Requires-Dist: tzlocal
Requires-Dist: zprocess >=2.2.2
Provides-Extra: docs
Requires-Dist: PyQt5 ; extra == 'docs'
Requires-Dist: Sphinx ==4.4.0 ; extra == 'docs'
Requires-Dist: sphinx-rtd-theme ==0.5.2 ; extra == 'docs'
Requires-Dist: recommonmark ==0.6.0 ; extra == 'docs'
Requires-Dist: m2r ==0.2.1 ; extra == 'docs'
Requires-Dist: mistune <2.0.0 ; extra == 'docs'
Provides-Extra: pyqt
Requires-Dist: PyQt5 ; extra == 'pyqt'
